giant_dipper/OrderManager.py
giant_dipper/OrderServices.py
giant_dipper/OrderSides.py
giant_dipper/OrderStatuses.py
giant_dipper/RobinHoodAuth.py
giant_dipper/StateManagers.py
giant_dipper/__init__.py
giant_dipper-0.1.3.dist-info/LICENSE
giant_dipper-0.1.3.dist-info/METADATA
giant_dipper-0.1.3.dist-info/WHEEL
giant_dipper-0.1.3.dist-info/top_level.txt
giant_dipper-0.1.3.dist-info/RECORD
