Metadata-Version: 2.1
Name: giant-dipper
Version: 0.1.3
Summary: Trading algorithm that thrives on assets that make big, volatile movements in the short-term, yet demonstrate little-to-no movement in the long-term.
Home-page: https://github.com/wheaney/giant-dipper
Author: Wayne Heaney
Author-email: wayne.heaney@gmail.com
License: GPL-3.0-only
License-File: LICENSE
Requires-Dist: robin-stocks
Requires-Dist: PyYAML
Requires-Dist: pyotp
